django_migration_cleaner/__init__.py
django_migration_cleaner/management/__init__.py
django_migration_cleaner/management/commands/__init__.py
django_migration_cleaner/management/commands/delete_migrations.py
django_migration_cleaner-1.0.4.dist-info/LICENSE
django_migration_cleaner-1.0.4.dist-info/METADATA
django_migration_cleaner-1.0.4.dist-info/WHEEL
django_migration_cleaner-1.0.4.dist-info/entry_points.txt
django_migration_cleaner-1.0.4.dist-info/top_level.txt
django_migration_cleaner-1.0.4.dist-info/RECORD
