Metadata-Version: 2.1
Name: django-migration-cleaner
Version: 1.0.4
Summary: A Django management command to delete migrations.
Home-page: https://github.com/Josephchinedu/Django-delete-migration.git
Author: Devjoseph
Author-email: joseph4jubilant@gmail.com
Classifier: Programming Language :: Python :: 3
Classifier: License :: OSI Approved :: MIT License
Classifier: Operating System :: OS Independent
Requires-Python: >=3.6
License-File: LICENSE
Requires-Dist: django>=3.2
